browser/__init__.py
browser/chrome.py
browser/driver_utils.py
browser/firefox.py
browser/web_elements.py
ibott_browser_manager-1.0.9.dist-info/LICENSE
ibott_browser_manager-1.0.9.dist-info/METADATA
ibott_browser_manager-1.0.9.dist-info/WHEEL
ibott_browser_manager-1.0.9.dist-info/top_level.txt
ibott_browser_manager-1.0.9.dist-info/RECORD
