Metadata-Version: 2.1
Name: ibott-browser-manager
Version: 1.0.9
Summary: This packages crates a simple way to work with, Chrome and Firefox Browsers.
Home-page: https://github.com/ecrespo66/files_and_folders
Author: OnameDohe
Author-email: OnameDohe <enrique.crespo.debenito@gmail.com>
License: Apache License
Project-URL: Homepage, https://github.com/ecrespo66/browser_manager
Project-URL: Bug Tracker, https://github.com/ecrespo66/browser_manager/issues
Classifier: Programming Language :: Python :: 3
Classifier: License :: OSI Approved :: MIT License
Classifier: Operating System :: OS Independent
Requires-Python: >=3.7
License-File: LICENSE
Requires-Dist: hatchling
Requires-Dist: selenium
Requires-Dist: webdriver-manager
